Dusky_data_crawler1/.idea/inspectionProfiles/profiles_settings.xml
Dusky_data_crawler1/.idea/misc.xml
Dusky_data_crawler1/.idea/modules.xml
Dusky_data_crawler1/.idea/pythonProject.iml
Dusky_data_crawler1/.idea/workspace.xml
Dusky_data_crawler1/Dusky_data_crawler1/.git/COMMIT_EDITMSG
Dusky_data_crawler1/Dusky_data_crawler1/.git/config
Dusky_data_crawler1/Dusky_data_crawler1/.git/description
Dusky_data_crawler1/Dusky_data_crawler1/.git/HEAD
Dusky_data_crawler1/Dusky_data_crawler1/.git/hooks/applypatch-msg.sample
Dusky_data_crawler1/Dusky_data_crawler1/.git/hooks/commit-msg.sample
Dusky_data_crawler1/Dusky_data_crawler1/.git/hooks/fsmonitor-watchman.sample
Dusky_data_crawler1/Dusky_data_crawler1/.git/hooks/post-update.sample
Dusky_data_crawler1/Dusky_data_crawler1/.git/hooks/pre-applypatch.sample
Dusky_data_crawler1/Dusky_data_crawler1/.git/hooks/pre-commit.sample
Dusky_data_crawler1/Dusky_data_crawler1/.git/hooks/pre-merge-commit.sample
Dusky_data_crawler1/Dusky_data_crawler1/.git/hooks/pre-push.sample
Dusky_data_crawler1/Dusky_data_crawler1/.git/hooks/pre-rebase.sample
Dusky_data_crawler1/Dusky_data_crawler1/.git/hooks/pre-receive.sample
Dusky_data_crawler1/Dusky_data_crawler1/.git/hooks/prepare-commit-msg.sample
Dusky_data_crawler1/Dusky_data_crawler1/.git/hooks/push-to-checkout.sample
Dusky_data_crawler1/Dusky_data_crawler1/.git/hooks/update.sample
Dusky_data_crawler1/Dusky_data_crawler1/.git/index
Dusky_data_crawler1/Dusky_data_crawler1/.git/info/exclude
Dusky_data_crawler1/Dusky_data_crawler1/.git/logs/HEAD
Dusky_data_crawler1/Dusky_data_crawler1/.git/logs/refs/heads/master
Dusky_data_crawler1/Dusky_data_crawler1/.git/objects/0b/cfa2d465a149a5cc0458198253101a24e3052c
Dusky_data_crawler1/Dusky_data_crawler1/.git/objects/15/e73cbd9072d85a122ed41ebae71128f09e52d1
Dusky_data_crawler1/Dusky_data_crawler1/.git/objects/22/f60ea4288a050cb3234496c89cf329b12d1a3c
Dusky_data_crawler1/Dusky_data_crawler1/.git/objects/42/eb559cf130249d17e05d1c74c0e74dcd990e84
dusky_data_crawler1-0.1.0.dist-info/METADATA
dusky_data_crawler1-0.1.0.dist-info/WHEEL
dusky_data_crawler1-0.1.0.dist-info/RECORD
