Metadata-Version: 2.1
Name: Dusky_data_crawler1
Version: 0.1.0
Summary: 
Author: DuskyRaven
Author-email: nkrucinskas@gmail.com
Requires-Python: >=3.11,<4.0
Classifier: Programming Language :: Python :: 3
Classifier: Programming Language :: Python :: 3.11
Classifier: Programming Language :: Python :: 3.12
Requires-Dist: ingrida-data-kup (>=0.1.0,<0.2.0)
Requires-Dist: requests (>=2.31.0,<3.0.0)
